{
"meta":{"test_sets":[],"test_metrics":[],"learn_metrics":[{"best_value":"Min","name":"MultiClass"}],"launch_mode":"Train","parameters":"","iteration_count":300,"learn_sets":["learn"],"name":"experiment"},
"iterations":[
{"learn":[1.185041843],"iteration":0,"passed_time":0.03435631373,"remaining_time":10.27253781},
{"learn":[0.9309435366],"iteration":1,"passed_time":0.06180790693,"remaining_time":9.209378133},
{"learn":[0.7654640467],"iteration":2,"passed_time":0.08569010011,"remaining_time":8.483319911},
{"learn":[0.6503109341],"iteration":3,"passed_time":0.1151370357,"remaining_time":8.520140643},
{"learn":[0.5617569835],"iteration":4,"passed_time":0.139825799,"remaining_time":8.249722144},
{"learn":[0.4946124185],"iteration":5,"passed_time":0.1851427671,"remaining_time":9.071995586},
{"learn":[0.4415123053],"iteration":6,"passed_time":0.2177282764,"remaining_time":9.113483568},
{"learn":[0.3954434953],"iteration":7,"passed_time":0.238563811,"remaining_time":8.707579101},
{"learn":[0.3573188793],"iteration":8,"passed_time":0.2581258664,"remaining_time":8.346069681},
{"learn":[0.3296777942],"iteration":9,"passed_time":0.2813801949,"remaining_time":8.160025651},
{"learn":[0.305110284],"iteration":10,"passed_time":0.3167846998,"remaining_time":8.322798022},
{"learn":[0.2829155504],"iteration":11,"passed_time":0.3682158179,"remaining_time":8.83717963},
{"learn":[0.2668336573],"iteration":12,"passed_time":0.4458389248,"remaining_time":9.842751648},
{"learn":[0.2512094092],"iteration":13,"passed_time":0.4894405458,"remaining_time":9.998571151},
{"learn":[0.2378091086],"iteration":14,"passed_time":0.5843380372,"remaining_time":11.10242271},
{"learn":[0.2272771308],"iteration":15,"passed_time":0.6731655027,"remaining_time":11.94868767},
{"learn":[0.2145365681],"iteration":16,"passed_time":0.6988898741,"remaining_time":11.63446085},
{"learn":[0.2032891737],"iteration":17,"passed_time":0.7226819855,"remaining_time":11.32201777},
{"learn":[0.1932833545],"iteration":18,"passed_time":0.7495036723,"remaining_time":11.08476484},
{"learn":[0.1854280498],"iteration":19,"passed_time":0.773700152,"remaining_time":10.83180213},
{"learn":[0.1777704886],"iteration":20,"passed_time":0.7974451807,"remaining_time":10.59462883},
{"learn":[0.1716892771],"iteration":21,"passed_time":0.8202071839,"remaining_time":10.36443623},
{"learn":[0.1657871631],"iteration":22,"passed_time":0.854682454,"remaining_time":10.29334955},
{"learn":[0.1613679024],"iteration":23,"passed_time":0.8796103384,"remaining_time":10.11551889},
{"learn":[0.1570749333],"iteration":24,"passed_time":0.9237847834,"remaining_time":10.16163262},
{"learn":[0.152172607],"iteration":25,"passed_time":1.021337773,"remaining_time":10.76332884},
{"learn":[0.1474324228],"iteration":26,"passed_time":1.083083848,"remaining_time":10.95118113},
{"learn":[0.1432262065],"iteration":27,"passed_time":1.15632111,"remaining_time":11.23283364},
{"learn":[0.1400539785],"iteration":28,"passed_time":1.2099439,"remaining_time":11.30671714},
{"learn":[0.1354639289],"iteration":29,"passed_time":1.236831544,"remaining_time":11.1314839},
{"learn":[0.1321242431],"iteration":30,"passed_time":1.26236571,"remaining_time":10.95407665},
{"learn":[0.1284586798],"iteration":31,"passed_time":1.287015683,"remaining_time":10.77875634},
{"learn":[0.1252610132],"iteration":32,"passed_time":1.31165353,"remaining_time":10.61246947},
{"learn":[0.1231132044],"iteration":33,"passed_time":1.349119502,"remaining_time":10.5548761},
{"learn":[0.1211926078],"iteration":34,"passed_time":1.384459924,"remaining_time":10.48233943},
{"learn":[0.1188250332],"iteration":35,"passed_time":1.407073055,"remaining_time":10.31853574},
{"learn":[0.1161686314],"iteration":36,"passed_time":1.444269155,"remaining_time":10.26602129},
{"learn":[0.1144166179],"iteration":37,"passed_time":1.462558565,"remaining_time":10.08395642},
{"learn":[0.1119191153],"iteration":38,"passed_time":1.519534301,"remaining_time":10.16919109},
{"learn":[0.1099046136],"iteration":39,"passed_time":1.543919944,"remaining_time":10.03547964},
{"learn":[0.1086116883],"iteration":40,"passed_time":1.624337047,"remaining_time":10.26105598},
{"learn":[0.1057159748],"iteration":41,"passed_time":1.752095627,"remaining_time":10.76287313},
{"learn":[0.1037374835],"iteration":42,"passed_time":1.808012171,"remaining_time":10.80602623},
{"learn":[0.1022999908],"iteration":43,"passed_time":1.839987816,"remaining_time":10.70538366},
{"learn":[0.1002288884],"iteration":44,"passed_time":1.879873247,"remaining_time":10.65261507},
{"learn":[0.09826993257],"iteration":45,"passed_time":1.920125507,"remaining_time":10.60243214},
{"learn":[0.09677673643],"iteration":46,"passed_time":1.941700071,"remaining_time":10.45213017},
{"learn":[0.09557781763],"iteration":47,"passed_time":1.972172031,"remaining_time":10.35390316},
{"learn":[0.09432806666],"iteration":48,"passed_time":1.998636557,"remaining_time":10.23791379},
{"learn":[0.0923130327],"iteration":49,"passed_time":2.019154305,"remaining_time":10.09577153},
{"learn":[0.09117053771],"iteration":50,"passed_time":2.038768068,"remaining_time":9.953985275},
{"learn":[0.09029306999],"iteration":51,"passed_time":2.080678175,"remaining_time":9.923234375},
{"learn":[0.08797984323],"iteration":52,"passed_time":2.097769771,"remaining_time":9.776398745},
{"learn":[0.08608288338],"iteration":53,"passed_time":2.11826852,"remaining_time":9.649889922},
{"learn":[0.08476162533],"iteration":54,"passed_time":2.14657464,"remaining_time":9.562014308},
{"learn":[0.08373756917],"iteration":55,"passed_time":2.190844334,"remaining_time":9.545821741},
{"learn":[0.08268347637],"iteration":56,"passed_time":2.275918569,"remaining_time":9.702600216},
{"learn":[0.08157360506],"iteration":57,"passed_time":2.371462758,"remaining_time":9.894723922},
{"learn":[0.08035899813],"iteration":58,"passed_time":2.423413285,"remaining_time":9.899027145},
{"learn":[0.07964349478],"iteration":59,"passed_time":2.509590585,"remaining_time":10.03836234},
{"learn":[0.07844972184],"iteration":60,"passed_time":2.53599032,"remaining_time":9.936093222},
{"learn":[0.07773601687],"iteration":61,"passed_time":2.580154099,"remaining_time":9.904462509},
{"learn":[0.07668351551],"iteration":62,"passed_time":2.612191825,"remaining_time":9.826816867},
{"learn":[0.07564560855],"iteration":63,"passed_time":2.63924105,"remaining_time":9.732201373},
{"learn":[0.07499069215],"iteration":64,"passed_time":2.674678721,"remaining_time":9.6699923},
{"learn":[0.07390485277],"iteration":65,"passed_time":2.755312612,"remaining_time":9.768835626},
{"learn":[0.07334550635],"iteration":66,"passed_time":2.813022711,"remaining_time":9.782601369},
{"learn":[0.07221302794],"iteration":67,"passed_time":2.846520039,"remaining_time":9.711656604},
{"learn":[0.07097393708],"iteration":68,"passed_time":2.937351513,"remaining_time":9.833742023},
{"learn":[0.07014195574],"iteration":69,"passed_time":3.002552407,"remaining_time":9.865529336},
{"learn":[0.06903330592],"iteration":70,"passed_time":3.087868638,"remaining_time":9.959463635},
{"learn":[0.06817592845],"iteration":71,"passed_time":3.151815343,"remaining_time":9.980748587},
{"learn":[0.06717260803],"iteration":72,"passed_time":3.189098317,"remaining_time":9.916785179},
{"learn":[0.06625493008],"iteration":73,"passed_time":3.212896804,"remaining_time":9.812360508},
{"learn":[0.06536085912],"iteration":74,"passed_time":3.247014955,"remaining_time":9.741044864},
{"learn":[0.0645741952],"iteration":75,"passed_time":3.27200613,"remaining_time":9.64380754},
{"learn":[0.06397969563],"iteration":76,"passed_time":3.318938863,"remaining_time":9.611991772},
{"learn":[0.06331905897],"iteration":77,"passed_time":3.350908591,"remaining_time":9.537201373},
{"learn":[0.06255828481],"iteration":78,"passed_time":3.398838391,"remaining_time":9.508142841},
{"learn":[0.06200098265],"iteration":79,"passed_time":3.42694989,"remaining_time":9.424112198},
{"learn":[0.06123044723],"iteration":80,"passed_time":3.455655213,"remaining_time":9.343067798},
{"learn":[0.06057074624],"iteration":81,"passed_time":3.512511534,"remaining_time":9.338140419},
{"learn":[0.05995646073],"iteration":82,"passed_time":3.608275261,"remaining_time":9.433683514},
{"learn":[0.05931614528],"iteration":83,"passed_time":3.683093539,"remaining_time":9.470811957},
{"learn":[0.05880510708],"iteration":84,"passed_time":3.785235787,"remaining_time":9.574419931},
{"learn":[0.05840840883],"iteration":85,"passed_time":3.822608218,"remaining_time":9.512071612},
{"learn":[0.05814225909],"iteration":86,"passed_time":3.878778592,"remaining_time":9.496320001},
{"learn":[0.05761324681],"iteration":87,"passed_time":3.926077194,"remaining_time":9.458276877},
{"learn":[0.05697942144],"iteration":88,"passed_time":3.967405227,"remaining_time":9.40587082},
{"learn":[0.05597382081],"iteration":89,"passed_time":4.015985017,"remaining_time":9.370631707},
{"learn":[0.05527939831],"iteration":90,"passed_time":4.031283559,"remaining_time":9.25866224},
{"learn":[0.05463021738],"iteration":91,"passed_time":4.077828632,"remaining_time":9.219438646},
{"learn":[0.053759287],"iteration":92,"passed_time":4.098816706,"remaining_time":9.123172667},
{"learn":[0.0531549167],"iteration":93,"passed_time":4.123344722,"remaining_time":9.036266092},
{"learn":[0.05265551039],"iteration":94,"passed_time":4.177734458,"remaining_time":9.015111199},
{"learn":[0.05209755163],"iteration":95,"passed_time":4.286920299,"remaining_time":9.109705636},
{"learn":[0.05151825821],"iteration":96,"passed_time":4.364847401,"remaining_time":9.134680644},
{"learn":[0.05120811946],"iteration":97,"passed_time":4.409646961,"remaining_time":9.089272308},
{"learn":[0.05087318701],"iteration":98,"passed_time":4.46019426,"remaining_time":9.055545922},
{"learn":[0.05049013458],"iteration":99,"passed_time":4.497408736,"remaining_time":8.994817471},
{"learn":[0.05005126487],"iteration":100,"passed_time":4.521982668,"remaining_time":8.909649018},
{"learn":[0.04980512572],"iteration":101,"passed_time":4.572757963,"remaining_time":8.876530164},
{"learn":[0.04925970609],"iteration":102,"passed_time":4.60251981,"remaining_time":8.802877695},
{"learn":[0.04900506983],"iteration":103,"passed_time":4.620935051,"remaining_time":8.708685288},
{"learn":[0.04843936378],"iteration":104,"passed_time":4.636790459,"remaining_time":8.61118228},
{"learn":[0.04810729326],"iteration":105,"passed_time":4.656113226,"remaining_time":8.521565716},
{"learn":[0.04747210248],"iteration":106,"passed_time":4.711779484,"remaining_time":8.498817199},
{"learn":[0.04690272807],"iteration":107,"passed_time":4.733694126,"remaining_time":8.415456223},
{"learn":[0.04655423312],"iteration":108,"passed_time":4.827164515,"remaining_time":8.45860938},
{"learn":[0.04611417126],"iteration":109,"passed_time":4.953254164,"remaining_time":8.555620828},
{"learn":[0.04565375137],"iteration":110,"passed_time":5.010895514,"remaining_time":8.532065334},
{"learn":[0.04531495587],"iteration":111,"passed_time":5.048127489,"remaining_time":8.47364257},
{"learn":[0.04488619688],"iteration":112,"passed_time":5.072700171,"remaining_time":8.394645415},
{"learn":[0.04464365846],"iteration":113,"passed_time":5.104671398,"remaining_time":8.328674387},
{"learn":[0.04451711442],"iteration":114,"passed_time":5.135273523,"remaining_time":8.26109219},
{"learn":[0.0439222756],"iteration":115,"passed_time":5.162887531,"remaining_time":8.189407807},
{"learn":[0.04363122861],"iteration":116,"passed_time":5.192712168,"remaining_time":8.121934417},
{"learn":[0.04324863974],"iteration":117,"passed_time":5.223797286,"remaining_time":8.057043271},
{"learn":[0.04253139861],"iteration":118,"passed_time":5.256360087,"remaining_time":7.994967863},
{"learn":[0.04234834336],"iteration":119,"passed_time":5.296232394,"remaining_time":7.944348591},
{"learn":[0.0418816343],"iteration":120,"passed_time":5.337226558,"remaining_time":7.89556656},
{"learn":[0.0413412375],"iteration":121,"passed_time":5.363011511,"remaining_time":7.824721713},
{"learn":[0.04105655517],"iteration":122,"passed_time":5.387984187,"remaining_time":7.753440659},
{"learn":[0.04075641574],"iteration":123,"passed_time":5.43969955,"remaining_time":7.720863878},
{"learn":[0.0404404194],"iteration":124,"passed_time":5.57118761,"remaining_time":7.799662655},
{"learn":[0.04009300399],"iteration":125,"passed_time":5.645376232,"remaining_time":7.795995749},
{"learn":[0.03982649712],"iteration":126,"passed_time":5.684960377,"remaining_time":7.744079883},
{"learn":[0.03959696287],"iteration":127,"passed_time":5.710669748,"remaining_time":7.673712474},
{"learn":[0.03934618795],"iteration":128,"passed_time":5.728705787,"remaining_time":7.593865811},
{"learn":[0.03892618917],"iteration":129,"passed_time":5.750890425,"remaining_time":7.520395171},
{"learn":[0.03859100195],"iteration":130,"passed_time":5.775062946,"remaining_time":7.450272045},
{"learn":[0.03827019709],"iteration":131,"passed_time":5.800346492,"remaining_time":7.382259171},
{"learn":[0.03787656275],"iteration":132,"passed_time":5.81940493,"remaining_time":7.307072356},
{"learn":[0.03768585012],"iteration":133,"passed_time":5.839349854,"remaining_time":7.233821462},
{"learn":[0.03742931051],"iteration":134,"passed_time":5.861911778,"remaining_time":7.164558839},
{"learn":[0.0371298048],"iteration":135,"passed_time":5.887241405,"remaining_time":7.099320518},
{"learn":[0.0369074637],"iteration":136,"passed_time":5.909463667,"remaining_time":7.030967721},
{"learn":[0.03660490594],"iteration":137,"passed_time":5.939565634,"remaining_time":6.97253357},
{"learn":[0.03635397956],"iteration":138,"passed_time":5.971721192,"remaining_time":6.916885697},
{"learn":[0.03609441283],"iteration":139,"passed_time":6.010693514,"remaining_time":6.869364016},
{"learn":[0.03585429911],"iteration":140,"passed_time":6.091468277,"remaining_time":6.869102526},
{"learn":[0.03561303592],"iteration":141,"passed_time":6.156772169,"remaining_time":6.850492977},
{"learn":[0.03538338168],"iteration":142,"passed_time":6.21839637,"remaining_time":6.827190421},
{"learn":[0.03517791822],"iteration":143,"passed_time":6.281241635,"remaining_time":6.804678438},
{"learn":[0.03478532135],"iteration":144,"passed_time":6.30935476,"remaining_time":6.744482674},
{"learn":[0.03466047207],"iteration":145,"passed_time":6.33296829,"remaining_time":6.679980252},
{"learn":[0.03449121732],"iteration":146,"passed_time":6.359330526,"remaining_time":6.618895038},
{"learn":[0.03428264361],"iteration":147,"passed_time":6.392600191,"remaining_time":6.565373169},
{"learn":[0.03386646278],"iteration":148,"passed_time":6.424725291,"remaining_time":6.510963215},
{"learn":[0.03359303152],"iteration":149,"passed_time":6.446855097,"remaining_time":6.446855097},
{"learn":[0.03341315714],"iteration":150,"passed_time":6.466435568,"remaining_time":6.380787415},
{"learn":[0.03313009332],"iteration":151,"passed_time":6.487301061,"remaining_time":6.316582612},
{"learn":[0.03291551167],"iteration":152,"passed_time":6.50655183,"remaining_time":6.251392934},
{"learn":[0.03272633988],"iteration":153,"passed_time":6.525742974,"remaining_time":6.186743339},
{"learn":[0.03254815117],"iteration":154,"passed_time":6.561179271,"remaining_time":6.137877382},
{"learn":[0.03229109969],"iteration":155,"passed_time":6.582273218,"remaining_time":6.075944509},
{"learn":[0.03205890025],"iteration":156,"passed_time":6.603450455,"remaining_time":6.014607739},
{"learn":[0.03196770421],"iteration":157,"passed_time":6.635860384,"remaining_time":5.963874522},
{"learn":[0.03170851382],"iteration":158,"passed_time":6.70405352,"remaining_time":5.945104065},
{"learn":[0.0315646192],"iteration":159,"passed_time":6.778128476,"remaining_time":5.930862417},
{"learn":[0.03124471468],"iteration":160,"passed_time":6.843602115,"remaining_time":5.908451515},
{"learn":[0.03117073872],"iteration":161,"passed_time":6.909673994,"remaining_time":5.886018587},
{"learn":[0.03100505742],"iteration":162,"passed_time":6.933189193,"remaining_time":5.827281714},
{"learn":[0.03066854918],"iteration":163,"passed_time":6.954901672,"remaining_time":5.767479435},
{"learn":[0.03048428607],"iteration":164,"passed_time":6.975118966,"remaining_time":5.706915518},
{"learn":[0.03028629633],"iteration":165,"passed_time":6.997399519,"remaining_time":5.648503226},
{"learn":[0.03021595289],"iteration":166,"passed_time":7.021694081,"remaining_time":5.592127621},
{"learn":[0.02995865018],"iteration":167,"passed_time":7.04509599,"remaining_time":5.535432564},
{"learn":[0.02986338427],"iteration":168,"passed_time":7.065053664,"remaining_time":5.476461716},
{"learn":[0.02971987513],"iteration":169,"passed_time":7.087404757,"remaining_time":5.419780108},
{"learn":[0.02957817168],"iteration":170,"passed_time":7.109813974,"remaining_time":5.363543875},
{"learn":[0.02951840907],"iteration":171,"passed_time":7.129151867,"remaining_time":5.305415343},
{"learn":[0.02932184048],"iteration":172,"passed_time":7.153899796,"remaining_time":5.251706787},
{"learn":[0.02908792035],"iteration":173,"passed_time":7.175860979,"remaining_time":5.196313122},
{"learn":[0.02888164756],"iteration":174,"passed_time":7.228107042,"remaining_time":5.162933601},
{"learn":[0.02860304237],"iteration":175,"passed_time":7.288661553,"remaining_time":5.135193367},
{"learn":[0.02849346972],"iteration":176,"passed_time":7.381681908,"remaining_time":5.12964336},
{"learn":[0.02838234645],"iteration":177,"passed_time":7.486121993,"remaining_time":5.130937546},
{"learn":[0.02815763677],"iteration":178,"passed_time":7.524765612,"remaining_time":5.086573403},
{"learn":[0.02800455579],"iteration":179,"passed_time":7.546785336,"remaining_time":5.031190224},
{"learn":[0.02789978199],"iteration":180,"passed_time":7.584642092,"remaining_time":4.986587895},
{"learn":[0.02774293249],"iteration":181,"passed_time":7.612940047,"remaining_time":4.935862228},
{"learn":[0.0275070331],"iteration":182,"passed_time":7.63322909,"remaining_time":4.880261222},
{"learn":[0.02743482076],"iteration":183,"passed_time":7.653498592,"remaining_time":4.825031721},
{"learn":[0.02720994322],"iteration":184,"passed_time":7.672010207,"remaining_time":4.769087426},
{"learn":[0.02709115817],"iteration":185,"passed_time":7.691491638,"remaining_time":4.714140036},
{"learn":[0.02687427018],"iteration":186,"passed_time":7.725797786,"remaining_time":4.668530213},
{"learn":[0.02675929227],"iteration":187,"passed_time":7.751978692,"remaining_time":4.618200072},
{"learn":[0.02655376761],"iteration":188,"passed_time":7.768884166,"remaining_time":4.562678002},
{"learn":[0.02644027601],"iteration":189,"passed_time":7.817851616,"remaining_time":4.52612462},
{"learn":[0.02628285244],"iteration":190,"passed_time":7.887590018,"remaining_time":4.501294827},
{"learn":[0.02613560348],"iteration":191,"passed_time":7.986014243,"remaining_time":4.492133012},
{"learn":[0.02588366162],"iteration":192,"passed_time":8.06960092,"remaining_time":4.473820199},
{"learn":[0.02573189163],"iteration":193,"passed_time":8.11821225,"remaining_time":4.435724219},
{"learn":[0.02556947726],"iteration":194,"passed_time":8.19149847,"remaining_time":4.410806868},
{"learn":[0.02547027426],"iteration":195,"passed_time":8.251734319,"remaining_time":4.378471271},
{"learn":[0.02533938272],"iteration":196,"passed_time":8.29751753,"remaining_time":4.338295967},
{"learn":[0.02525224318],"iteration":197,"passed_time":8.322072253,"remaining_time":4.287128131},
{"learn":[0.02508765622],"iteration":198,"passed_time":8.342879497,"remaining_time":4.234325775},
{"learn":[0.02502534201],"iteration":199,"passed_time":8.363442286,"remaining_time":4.181721143},
{"learn":[0.02487538865],"iteration":200,"passed_time":8.383850036,"remaining_time":4.129358973},
{"learn":[0.02475105438],"iteration":201,"passed_time":8.402128529,"remaining_time":4.076280177},
{"learn":[0.02465735611],"iteration":202,"passed_time":8.423777925,"remaining_time":4.025154969},
{"learn":[0.02455156843],"iteration":203,"passed_time":8.44861102,"remaining_time":3.97581695},
{"learn":[0.02442978035],"iteration":204,"passed_time":8.507296269,"remaining_time":3.942405588},
{"learn":[0.02437360427],"iteration":205,"passed_time":8.573863598,"remaining_time":3.912345525},
{"learn":[0.02421151838],"iteration":206,"passed_time":8.611552149,"remaining_time":3.868958212},
{"learn":[0.02410671007],"iteration":207,"passed_time":8.699206342,"remaining_time":3.847725882},
{"learn":[0.02392014087],"iteration":208,"passed_time":8.862679963,"remaining_time":3.858870223},
{"learn":[0.02375462877],"iteration":209,"passed_time":8.931897624,"remaining_time":3.827956125},
{"learn":[0.02361291464],"iteration":210,"passed_time":8.95594319,"remaining_time":3.777625326},
{"learn":[0.02349483555],"iteration":211,"passed_time":8.979068687,"remaining_time":3.727160587},
{"learn":[0.02343152355],"iteration":212,"passed_time":9.002542637,"remaining_time":3.67709488},
{"learn":[0.02326903664],"iteration":213,"passed_time":9.028759709,"remaining_time":3.62838007},
{"learn":[0.02321271323],"iteration":214,"passed_time":9.065914727,"remaining_time":3.584198845},
{"learn":[0.02301112871],"iteration":215,"passed_time":9.097082551,"remaining_time":3.537754325},
{"learn":[0.02295597596],"iteration":216,"passed_time":9.118935402,"remaining_time":3.487887734},
{"learn":[0.02292404444],"iteration":217,"passed_time":9.14028122,"remaining_time":3.438087431},
{"learn":[0.02278569053],"iteration":218,"passed_time":9.161896492,"remaining_time":3.388646648},
{"learn":[0.02248149603],"iteration":219,"passed_time":9.181957956,"remaining_time":3.338893802},
{"learn":[0.02237769072],"iteration":220,"passed_time":9.202311332,"remaining_time":3.289514005},
{"learn":[0.02228027579],"iteration":221,"passed_time":9.224779673,"remaining_time":3.241138804},
{"learn":[0.02220111231],"iteration":222,"passed_time":9.267966801,"remaining_time":3.200149972},
{"learn":[0.02209770084],"iteration":223,"passed_time":9.324755956,"remaining_time":3.163756485},
{"learn":[0.02190071212],"iteration":224,"passed_time":9.394673022,"remaining_time":3.131557674},
{"learn":[0.02172024512],"iteration":225,"passed_time":9.449567042,"remaining_time":3.094106023},
{"learn":[0.02161347219],"iteration":226,"passed_time":9.523552584,"remaining_time":3.062640258},
{"learn":[0.02151381926],"iteration":227,"passed_time":9.54716324,"remaining_time":3.014893655},
{"learn":[0.02143107856],"iteration":228,"passed_time":9.572233705,"remaining_time":2.96781045},
{"learn":[0.02133868331],"iteration":229,"passed_time":9.595951192,"remaining_time":2.920506885},
{"learn":[0.02119926241],"iteration":230,"passed_time":9.619949925,"remaining_time":2.873491536},
{"learn":[0.02107738673],"iteration":231,"passed_time":9.642171979,"remaining_time":2.826153856},
{"learn":[0.0210159403],"iteration":232,"passed_time":9.667689687,"remaining_time":2.779979438},
{"learn":[0.02088964455],"iteration":233,"passed_time":9.687335575,"remaining_time":2.732325418},
{"learn":[0.02072662745],"iteration":234,"passed_time":9.709978413,"remaining_time":2.68573871},
{"learn":[0.02064333064],"iteration":235,"passed_time":9.734587428,"remaining_time":2.639888116},
{"learn":[0.02058632713],"iteration":236,"passed_time":9.755259257,"remaining_time":2.593170182},
{"learn":[0.02049079063],"iteration":237,"passed_time":9.778827663,"remaining_time":2.547425694},
{"learn":[0.02038011199],"iteration":238,"passed_time":9.799870111,"remaining_time":2.501222079},
{"learn":[0.02028513963],"iteration":239,"passed_time":9.822928984,"remaining_time":2.455732246},
{"learn":[0.02022052234],"iteration":240,"passed_time":9.847194755,"remaining_time":2.410724027},
{"learn":[0.02005197716],"iteration":241,"passed_time":9.870024548,"remaining_time":2.365543074},
{"learn":[0.01996011119],"iteration":242,"passed_time":9.951408927,"remaining_time":2.334281106},
{"learn":[0.01980209571],"iteration":243,"passed_time":10.13110582,"remaining_time":2.325171829},
{"learn":[0.01968054534],"iteration":244,"passed_time":10.20728341,"remaining_time":2.29143097},
{"learn":[0.01956134504],"iteration":245,"passed_time":10.22940526,"remaining_time":2.245479204},
{"learn":[0.0194625732],"iteration":246,"passed_time":10.2586057,"remaining_time":2.20123928},
{"learn":[0.0193799651],"iteration":247,"passed_time":10.28095859,"remaining_time":2.155684865},
{"learn":[0.01932392083],"iteration":248,"passed_time":10.31390359,"remaining_time":2.112486277},
{"learn":[0.01917723943],"iteration":249,"passed_time":10.34715784,"remaining_time":2.069431567},
{"learn":[0.0191115175],"iteration":250,"passed_time":10.36674673,"remaining_time":2.023787209},
{"learn":[0.01905012454],"iteration":251,"passed_time":10.38646853,"remaining_time":1.978374958},
{"learn":[0.01898258754],"iteration":252,"passed_time":10.41470444,"remaining_time":1.934747465},
{"learn":[0.01885640464],"iteration":253,"passed_time":10.44357205,"remaining_time":1.891355569},
{"learn":[0.01875901909],"iteration":254,"passed_time":10.46059294,"remaining_time":1.84598699},
{"learn":[0.01871623816],"iteration":255,"passed_time":10.47757046,"remaining_time":1.800832422},
{"learn":[0.01866880323],"iteration":256,"passed_time":10.50523375,"remaining_time":1.757685025},
{"learn":[0.01863387855],"iteration":257,"passed_time":10.60674985,"remaining_time":1.726680207},
{"learn":[0.01854728794],"iteration":258,"passed_time":10.70999403,"remaining_time":1.695404461},
{"learn":[0.01846257435],"iteration":259,"passed_time":10.77737639,"remaining_time":1.658057906},
{"learn":[0.01841134565],"iteration":260,"passed_time":10.8032036,"remaining_time":1.614271802},
{"learn":[0.01831838027],"iteration":261,"passed_time":10.83042578,"remaining_time":1.570825112},
{"learn":[0.01820104959],"iteration":262,"passed_time":10.8581949,"remaining_time":1.527578751},
{"learn":[0.01811272465],"iteration":263,"passed_time":10.89655244,"remaining_time":1.485893515},
{"learn":[0.01800331644],"iteration":264,"passed_time":10.91420032,"remaining_time":1.441498156},
{"learn":[0.01790655069],"iteration":265,"passed_time":10.95072164,"remaining_time":1.3997163},
{"learn":[0.01787447134],"iteration":266,"passed_time":10.98206413,"remaining_time":1.357333769},
{"learn":[0.01785085824],"iteration":267,"passed_time":11.00736588,"remaining_time":1.314312344},
{"learn":[0.01772216548],"iteration":268,"passed_time":11.03345063,"remaining_time":1.271512897},
{"learn":[0.01762335404],"iteration":269,"passed_time":11.0476881,"remaining_time":1.2275209},
{"learn":[0.01759196203],"iteration":270,"passed_time":11.06664396,"remaining_time":1.184253412},
{"learn":[0.01754217294],"iteration":271,"passed_time":11.08716608,"remaining_time":1.14132592},
{"learn":[0.0174627848],"iteration":272,"passed_time":11.10806282,"remaining_time":1.09859962},
{"learn":[0.0173754493],"iteration":273,"passed_time":11.14098124,"remaining_time":1.057173403},
{"learn":[0.01731723125],"iteration":274,"passed_time":11.27342991,"remaining_time":1.024857265},
{"learn":[0.01724021285],"iteration":275,"passed_time":11.36634065,"remaining_time":0.9883774474},
{"learn":[0.01717230333],"iteration":276,"passed_time":11.42635975,"remaining_time":0.9487591127},
{"learn":[0.01710438108],"iteration":277,"passed_time":11.45056348,"remaining_time":0.9061596997},
{"learn":[0.01705520283],"iteration":278,"passed_time":11.4828462,"remaining_time":0.8643002516},
{"learn":[0.01697783332],"iteration":279,"passed_time":11.50720768,"remaining_time":0.8219434055},
{"learn":[0.01686729546],"iteration":280,"passed_time":11.53094546,"remaining_time":0.7796724686},
{"learn":[0.01682550071],"iteration":281,"passed_time":11.55085992,"remaining_time":0.7372889312},
{"learn":[0.01671942449],"iteration":282,"passed_time":11.59776649,"remaining_time":0.6966856195},
{"learn":[0.01663708127],"iteration":283,"passed_time":11.6165496,"remaining_time":0.6544534986},
{"learn":[0.01656135881],"iteration":284,"passed_time":11.65059017,"remaining_time":0.6131889562},
{"learn":[0.01652858694],"iteration":285,"passed_time":11.67305643,"remaining_time":0.5714083565},
{"learn":[0.0164144017],"iteration":286,"passed_time":11.69004065,"remaining_time":0.5295140364},
{"learn":[0.01632496849],"iteration":287,"passed_time":11.70477349,"remaining_time":0.4876988955},
{"learn":[0.01628406146],"iteration":288,"passed_time":11.73163643,"remaining_time":0.4465328744},
{"learn":[0.01621952027],"iteration":289,"passed_time":11.75187022,"remaining_time":0.4052369042},
{"learn":[0.01616553336],"iteration":290,"passed_time":11.83798657,"remaining_time":0.3661232958},
{"learn":[0.0160660192],"iteration":291,"passed_time":11.91834342,"remaining_time":0.3265299567},
{"learn":[0.01601980163],"iteration":292,"passed_time":11.98141256,"remaining_time":0.2862453512},
{"learn":[0.0159602626],"iteration":293,"passed_time":12.00706418,"remaining_time":0.2450421261},
{"learn":[0.01588635539],"iteration":294,"passed_time":12.03780443,"remaining_time":0.2040305835},
{"learn":[0.01586968024],"iteration":295,"passed_time":12.06775164,"remaining_time":0.1630777249},
{"learn":[0.01576828882],"iteration":296,"passed_time":12.10793674,"remaining_time":0.1223023913},
{"learn":[0.01570714479],"iteration":297,"passed_time":12.13150964,"remaining_time":0.08141952782},
{"learn":[0.01566544391],"iteration":298,"passed_time":12.15259213,"remaining_time":0.04064412085},
{"learn":[0.01555793382],"iteration":299,"passed_time":12.17347288,"remaining_time":0}
]}